{
  "id": "https://electrek.co/2025/04/07/world-surges-past-40-percent-clean-power-in-record-renewable-boom/",
  "title": "World surges past 40% clean power in record renewables boom | Electrek",
  "description": "Renewables and nuclear provided 40.9% of the world’s power generation in 2024, passing the 40% mark for the first time since the 1940s. ",
  "date": "2025-04-07",
  "link": "https://electrek.co/2025/04/07/world-surges-past-40-percent-clean-power-in-record-renewable-boom/",
  "category": "T-10 ENERGY",
  "bodyText": "Renewables and nuclear provided 40.9% of the world’s power generation in 2024, passing the 40% mark for the first time since the 1940s, according to a new global energy think tank Ember report. Renewables added a record 858 TWh in 2024, 49% more than the previous high in 2022. Solar was the largest contributor for the third year running, adding 474 TWh to reach a share of 6.9%. Solar was the fastest-growing power source (+29%) for the 20th year in a row. Solar has doubled in just three years, providing more than 2,000 TWh of electricity in 2024. Wind generation also grew to 8.1% of global electricity, while hydro – the single largest renewable source – remained steady at 14% of global electricity. “Solar power has become the engine of the global energy transition,” said Phil MacDonald, Ember’s managing director. “Paired with battery storage, solar is set to be an unstoppable force. As the fastest-growing and largest source of new electricity, it is critical in meeting the world’s ever-increasing demand for electricity.” Ember’s sixth annual Global Electricity Review, published today, provides the first comprehensive overview of the global power system in 2024 based on country-level data. It’s published alongside the world’s first open dataset on electricity generation in 2024, covering 88 countries that account for 93% of global electricity demand, as well as historical data for 215 countries. The analysis finds that fossil fuels also saw a small 1.4% increase in 2024 due to surging electricity demand, pushing global power sector emissions up 1.6% to an all-time high. Heatwaves were the main driver of the rise in fossil generation, accounting for almost a fifth (+0.7%) of the increase in global electricity demand in 2024 (+4.0%), mainly through additional use of cooling. Without these temperature effects, fossil fuel generation would have risen by only 0.2%, as clean electricity generation met 96% of the demand growth not caused by hotter temperatures. “Amid the noise, it’s essential to focus on the real signal,” continued MacDonald. “Hotter weather drove the fossil generation increase in 2024, but we’re very unlikely to see a similar jump in 2025.” Aside from weather effects, the increasing use of electricity for AI, data centers, EVs, and heat pumps is already contributing to global demand growth. Combined, the growing use of these technologies accounted for a 0.7% increase in global electricity demand in 2024, double what they contributed five years ago. Ember’s report shows that clean generation growth is set to outpace faster-rising demand in the coming years, marking the start of a permanent decline in fossil fuel generation. The current expected growth in clean generation would be sufficient to meet a demand increase of 4.1% per year to 2030, which is above expectations for demand growth. “The world is watching how technologies like AI and EVs will drive electricity demand,” said MacDonald. “It’s clear that booming solar and wind are comfortably set to deliver, and those expecting fossil fuel generation to keep rising will be disappointed.” Beyond emerging technologies, the growth trajectories of the world’s largest emerging economies will play a crucial role in defining the global outlook. More than half of the increase in solar generation in 2024 was in China, with its clean generation growth meeting 81% of its demand increase in 2024. India’s solar capacity additions in 2024 doubled compared to 2023. These two countries are at the forefront of the drive to clean power and will help tip the balance toward a decline in fossil generation at a global level. Professor Xunpeng Shi, president of the International Society for Energy Transition Studies (ISETS), said: “The future of the global power system is being shaped in Asia, with China and India at the heart of the energy transition. Their increasing reliance on renewables to power demand growth marks a shift that will redefine the global power sector and accelerate the decline of fossil fuels.” Read more: Made-in-America solar just got a big win in Louisiana If you live in an area that has frequent natural disaster events, and are interested in making your home more resilient to power outages, consider going solar and adding a battery storage system. To make sure you find a trusted, reliable solar installer near you that offers competitive pricing, check out EnergySage, a free service that makes it easy for you to go solar. They have hundreds of pre-vetted solar installers competing for your business, ensuring you get high quality solutions and save 20-30% compared to going it alone. Plus, it’s free to use and you won’t get sales calls until you select an installer and share your phone number with them. Your personalized solar quotes are easy to compare online and you’ll get access to unbiased Energy Advisers to help you every step of the way. Get started here. –trusted affiliate link* FTC: We use income earning auto affiliate links. More."
}